task2/rom.sv
module rom #(
    parameter ADDRESS_WIDTH = 8,
    DATA_WIDTH = 8
)(
    input logic                     clk,
    input logic [ADDRESS_WIDTH-1:0] addr1,
    input logic [ADDRESS_WIDTH-1:0] addr2,
    output logic [DATA_WIDTH-1:0]   dout1,
    output logic [DATA_WIDTH-1:0]   dout2
);

logic [DATA_WIDTH-1:0] rom_array [2**ADDRESS_WIDTH-1:0];

initial begin
        $display("Loading rom.");
        $readmemh("sinerom.mem", rom_array);
end;

always_ff @(posedge clk)

    dout1 <= rom_array [addr1];
    dout2 <= rom_array [addr2];

endmodule

task2/counter.sv
module counter #(
    parameter WIDTH = 8
)(

    input   logic               clk,
    input   logic               rst,
    input   logic               en,
    input  logic [WIDTH-1:0]    incr,
    output  logic  [WIDTH-1:0]  count1,
    output  logic  [WIDTH-1:0]  count2
);

always_ff @ (posedge clk) begin
  if (rst) begin
    count1 <= {WIDTH{1'b0}};
    count2 <= {WIDTH{1'b0}};
  end else begin
    count1 <= count1 + {{WIDTH - 1{1'b0}}, en};
    count2 <= count2 + incr; 
  end
end
endmodule

task2/sinegen.sv
module sinegen #(
  parameter WIDTH = 8
)(
  // interface signals
  input  logic             clk,      // clock 
  input  logic             rst,      // reset 
  input  logic             en,       // enable
  input  logic [WIDTH-1:0] incr,        // value to preload
  output logic [7:0]       dout1,
  output logic [7:0]       dout2      // count output
);

  logic  [WIDTH-1:0]       addr1;    // interconnect wire
  logic  [WIDTH-1:0]       addr2; 
counter myCounter (
  .clk (clk),
  .rst (rst),
  .en (en),
  .incr(incr),
  .count1 (addr1),
  .count2 (addr2)
);

rom myRom (
  .clk(clk),
  .addr1(addr1),
  .addr2(addr2),
  .dout1(dout1),
  .dout2(dout2)
);

endmodule

task2/sinegen.vcd
$version Generated by VerilatedVcd $end
$date Tue Nov  7 23:01:57 2023
 $end
$timescale   1ps $end

 $scope module TOP $end
  $var wire  1 # clk $end
  $var wire  8 ' dout1 [7:0] $end
  $var wire  8 ( dout2 [7:0] $end
  $var wire  1 % en $end
  $var wire  8 & incr [7:0] $end
  $var wire  1 $ rst $end
  $scope module sinegen $end
   $var wire 32 + WIDTH [31:0] $end
   $var wire  8 ) addr1 [7:0] $end
   $var wire  8 * addr2 [7:0] $end
   $var wire  1 # clk $end
   $var wire  8 ' dout1 [7:0] $end
   $var wire  8 ( dout2 [7:0] $end
   $var wire  1 % en $end
   $var wire  8 & incr [7:0] $end
   $var wire  1 $ rst $end
   $scope module myCounter $end
    $var wire 32 + WIDTH [31:0] $end
    $var wire  1 # clk $end
    $var wire  8 ) count1 [7:0] $end
    $var wire  8 * count2 [7:0] $end
    $var wire  1 % en $end
    $var wire  8 & incr [7:0] $end
    $var wire  1 $ rst $end
   $upscope $end
   $scope module myRom $end
    $var wire 32 + ADDRESS_WIDTH [31:0] $end
    $var wire 32 + DATA_WIDTH [31:0] $end
    $var wire  8 ) addr1 [7:0] $end
    $var wire  8 * addr2 [7:0] $end
    $var wire  1 # clk $end
    $var wire  8 ' dout1 [7:0] $end
    $var wire  8 ( dout2 [7:0] $end
   $upscope $end
  $upscope $end
 $upscope $end
$enddefinitions $end


#0
1#
0$
1%
b00000001 &
b00000000 '
b00000000 (
b00000000 )
b00000000 *
b00000000000000000000000000001000 +
#1
0#
#4
1#
b00001110 &
b11111110 '
b11111110 (
b00000001 )
b00000001 *
#5
0#
#8
1#
b11111101 '
b11111101 (
b00000010 )
b00001111 *
#9
0#
#12
1#
b11110101 (
b00000011 )
b00010000 *
#13
0#
#16
1#
b11110100 (
b00000100 )
b00010001 *
#17
0#
#20
1#
b11110011 (
b00000101 )
b00010010 *
#21
0#
#24
1#
b11110001 (
b00000110 )
b00010011 *
#25
0#
#28
1#
b11111100 '
b11110000 (
b00000111 )
b00010100 *
#29
0#
#32
1#
b11101111 (
b00001000 )
b00010101 *
#33
0#
#36
1#
b11111011 '
b11101101 (
b00001001 )
b00010110 *
#37
0#
#40
1#
b11111010 '
b11101011 (
b00001010 )
b00010111 *
#41
0#
#44
1#
b11101010 (
b00001011 )
b00011000 *
#45
0#
#48
1#
b11111001 '
b11101000 (
b00001100 )
b00011001 *
#49
0#
#52
1#
b11111000 '
b11100110 (
b00001101 )
b00011010 *
#53
0#
#56
1#
b11110111 '
b11100101 (
b00001110 )
b00011011 *
#57
0#
#60
1#
b11110110 '
b11100011 (
b00001111 )
b00011100 *
#61
0#
#64
1#
b11110101 '
b11100001 (
b00010000 )
b00011101 *
#65
0#
#68
1#
b11110100 '
b11011111 (
b00010001 )
b00011110 *
#69
0#
#72
1#
b11110011 '
b11011101 (
b00010010 )
b00011111 *
#73
0#
#76
1#
b11110001 '
b11011010 (
b00010011 )
b00100000 *
#77
0#
#80
1#
b11110000 '
b11011000 (
b00010100 )
b00100001 *
#81
0#
#84
1#
b11101111 '
b11010110 (
b00010101 )
b00100010 *
#85
0#
#88
1#
b11101101 '
b11010100 (
b00010110 )
b00100011 *
#89
0#
#92
1#
b11101011 '
b11010001 (
b00010111 )
b00100100 *
#93
0#
#96
1#
b11101010 '
b11001111 (
b00011000 )
b00100101 *
#97
0#
#100
1#
b11101000 '
b11001101 (
b00011001 )
b00100110 *
#101
0#
#104
1#
b11100110 '
b11001010 (
b00011010 )
b00100111 *
#105
0#
#108
1#
b11100101 '
b11001000 (
b00011011 )
b00101000 *
#109
0#
#112
1#
b11100011 '
b11000101 (
b00011100 )
b00101001 *
#113
0#
#116
1#
b11100001 '
b11000010 (
b00011101 )
b00101010 *
#117
0#
#120
1#
b11011111 '
b11000000 (
b00011110 )
b00101011 *
#121
0#
#124
1#
b11011101 '
b10111101 (
b00011111 )
b00101100 *
#125
0#
#128
1#
b11011010 '
b10111010 (
b00100000 )
b00101101 *
#129
0#
#132
1#
b11011000 '
b10111000 (
b00100001 )
b00101110 *
#133
0#
#136
1#
b11010110 '
b10110101 (
b00100010 )
b00101111 *
#137
0#
#140
1#
b11010100 '
b10110010 (
b00100011 )
b00110000 *
#141
0#
#144
1#
b11010001 '
b10101111 (
b00100100 )
b00110001 *
#145
0#
#148
1#
b11001111 '
b10101100 (
b00100101 )
b00110010 *
#149
0#
#152
1#
b11001101 '
b10101001 (
b00100110 )
b00110011 *
#153
0#
#156
1#
b11001010 '
b10100110 (
b00100111 )
b00110100 *
#157
0#
#160
1#
b11001000 '
b10100011 (
b00101000 )
b00110101 *
#161
0#
#164
1#
b11000101 '
b10100000 (
b00101001 )
b00110110 *
#165
0#
#168
1#
b11000010 '
b10011101 (
b00101010 )
b00110111 *
#169
0#
#172
1#
b11000000 '
b10011010 (
b00101011 )
b00111000 *
#173
0#
#176
1#
b10111101 '
b10010111 (
b00101100 )
b00111001 *
#177
0#
#180
1#
b10111010 '
b10010100 (
b00101101 )
b00111010 *
#181
0#
#184
1#
b10111000 '
b10010001 (
b00101110 )
b00111011 *
#185
0#
#188
1#
b10110101 '
b10001110 (
b00101111 )
b00111100 *
#189
0#
#192
1#
b10110010 '
b10001011 (
b00110000 )
b00111101 *
#193
0#
#196
1#
b10101111 '
b10001000 (
b00110001 )
b00111110 *
#197
0#
#200
1#
b10101100 '
b10000101 (
b00110010 )
b00111111 *
#201
0#
#204
1#
b10101001 '
b10000010 (
b00110011 )
b01000000 *
#205
0#
#208
1#
b10100110 '
b01111110 (
b00110100 )
b01000001 *
#209
0#
#212
1#
b10100011 '
b01111011 (
b00110101 )
b01000010 *
#213
0#
#216
1#
b10100000 '
b01111000 (
b00110110 )
b01000011 *
#217
0#
#220
1#
b10011101 '
b01110101 (
b00110111 )
b01000100 *
#221
0#
#224
1#
b10011010 '
b01110010 (
b00111000 )
b01000101 *
#225
0#
#228
1#
b10010111 '
b01101111 (
b00111001 )
b01000110 *
#229
0#
#232
1#
b10010100 '
b01101100 (
b00111010 )
b01000111 *
#233
0#
#236
1#
b10010001 '
b01101001 (
b00111011 )
b01001000 *
#237
0#
#240
1#
b10001110 '
b01100110 (
b00111100 )
b01001001 *
#241
0#
#244
1#
b10001011 '
b01100011 (
b00111101 )
b01001010 *
#245
0#
#248
1#
b10001000 '
b01100000 (
b00111110 )
b01001011 *
#249
0#
#252
1#
b10000101 '
b01011101 (
b00111111 )
b01001100 *
#253
0#
#256
1#
b10000010 '
b01011010 (
b01000000 )
b01001101 *
#257
0#
#260
1#
b01111110 '
b01010111 (
b01000001 )
b01001110 *
#261
0#
#264
1#
b01111011 '
b01010100 (
b01000010 )
b01001111 *
#265
0#
#268
1#
b01111000 '
b01010001 (
b01000011 )
b01010000 *
#269
0#
#272
1#
b01110101 '
b01001110 (
b01000100 )
b01010001 *
#273
0#
#276
1#
b01110010 '
b01001011 (
b01000101 )
b01010010 *
#277
0#
#280
1#
b01101111 '
b01001000 (
b01000110 )
b01010011 *
#281
0#
#284
1#
b01101100 '
b01000101 (
b01000111 )
b01010100 *
#285
0#
#288
1#
b01101001 '
b01000011 (
b01001000 )
b01010101 *
#289
0#
#292
1#
b01100110 '
b01000000 (
b01001001 )
b01010110 *
#293
0#
#296
1#
b01100011 '
b00111101 (
b01001010 )
b01010111 *
#297
0#
#300
1#
b01100000 '
b00111011 (
b01001011 )
b01011000 *
#301
0#
#304
1#
b01011101 '
b00111000 (
b01001100 )
b01011001 *
#305
0#
#308
1#
b01011010 '
b00110101 (
b01001101 )
b01011010 *
#309
0#
#312
1#
b01010111 '
b00110011 (
b01001110 )
b01011011 *
#313
0#
#316
1#
b01010100 '
b00110000 (
b01001111 )
b01011100 *
#317
0#
#320
1#
b01010001 '
b00101110 (
b01010000 )
b01011101 *
#321
0#
#324
1#
b01001110 '
b00101100 (
b01010001 )
b01011110 *
#325
0#
#328
1#
b01001011 '
b00101001 (
b01010010 )
b01011111 *
#329
0#
#332
1#
b01001000 '
b00100111 (
b01010011 )
b01100000 *
#333
0#
#336
1#
b01000101 '
b00100101 (
b01010100 )
b01100001 *
#337
0#
#340
1#
b01000011 '
b00100011 (
b01010101 )
b01100010 *
#341
0#
#344
1#
b01000000 '
b00100000 (
b01010110 )
b01100011 *
#345
0#
#348
1#
b00111101 '
b00011110 (
b01010111 )
b01100100 *
#349
0#
#352
1#
b00111011 '
b00011100 (
b01011000 )
b01100101 *
#353
0#
#356
1#
b00111000 '
b00011010 (
b01011001 )
b01100110 *
#357
0#
#360
1#
b00110101 '
b00011000 (
b01011010 )
b01100111 *
#361
0#
#364
1#
b00110011 '
b00010111 (
b01011011 )
b01101000 *
#365
0#
#368
1#
b00110000 '
b00010101 (
b01011100 )
b01101001 *
#369
0#
#372
1#
b00101110 '
b00010011 (
b01011101 )
b01101010 *
#373
0#
#376
1#
b00101100 '
b00010010 (
b01011110 )
b01101011 *
#377
0#
#380
1#
b00101001 '
b00010000 (
b01011111 )
b01101100 *
#381
0#
#384
1#
b00100111 '
b00001110 (
b01100000 )
b01101101 *
#385
0#
#388
1#
b00100101 '
b00001101 (
b01100001 )
b01101110 *
#389
0#
#392
1#
b00100011 '
b00001100 (
b01100010 )
b01101111 *
#393
0#
#396
1#
b00100000 '
b00001010 (
b01100011 )
b01110000 *
#397
0#
#400
1#
b00011110 '
b00001001 (
b01100100 )
b01110001 *
#401
0#
#404
1#
b00011100 '
b00001000 (
b01100101 )
b01110010 *
#405
0#
#408
1#
b00011010 '
b00000111 (
b01100110 )
b01110011 *
#409
0#
#412
1#
b00011000 '
b00000110 (
b01100111 )
b01110100 *
#413
0#
#416
1#
b00010111 '
b00000101 (
b01101000 )
b01110101 *
#417
0#
#420
1#
b00010101 '
b00000100 (
b01101001 )
b01110110 *
#421
0#
#424
1#
b00010011 '
b00000011 (
b01101010 )
b01110111 *
#425
0#
#428
1#
b00010010 '
b01101011 )
b01111000 *
#429
0#
#432
1#
b00010000 '
b00000010 (
b01101100 )
b01111001 *
#433
0#
#436
1#
b00001110 '
b00000001 (
b01101101 )
b01111010 *
#437
0#
#440
1#
b00001101 '
b01101110 )
b01111011 *
#441
0#
#444
1#
b00001100 '
b00000000 (
b01101111 )
b01111100 *
#445
0#
#448
1#
b00001010 '
b01110000 )
b01111101 *
#449
0#
#452
1#
b00001001 '
b01110001 )
b01111110 *
#453
0#
#456
1#
b00001000 '
b01110010 )
b01111111 *
#457
0#
#460
1#
b00000111 '
b01110011 )
b10000000 *
#461
0#
#464
1#
b00000110 '
b01110100 )
b10000001 *
#465
0#
#468
1#
b00000101 '
b01110101 )
b10000010 *
#469
0#
#472
1#
b00000100 '
b01110110 )
b10000011 *
#473
0#
#476
1#
b00000011 '
b01110111 )
b10000100 *
#477
0#
#480
1#
b01111000 )
b10000101 *
#481
0#
#484
1#
b00000010 '
b01111001 )
b10000110 *
#485
0#
#488
1#
b00000001 '
b00000001 (
b01111010 )
b10000111 *
#489
0#
#492
1#
b01111011 )
b10001000 *
#493
0#
#496
1#
b00000000 '
b00000010 (
b01111100 )
b10001001 *
#497
0#
#500
1#
b00000011 (
b01111101 )
b10001010 *
#501
0#
#504
1#
b01111110 )
b10001011 *
#505
0#
#508
1#
b00000100 (
b01111111 )
b10001100 *
#509
0#
#512
1#
b00000101 (
b10000000 )
b10001101 *
#513
0#
#516
1#
b00000110 (
b10000001 )
b10001110 *
#517
0#
#520
1#
b00000111 (
b10000010 )
b10001111 *
#521
0#
#524
1#
b00001000 (
b10000011 )
b10010000 *
#525
0#
#528
1#
b00001001 (
b10000100 )
b10010001 *
#529
0#
#532
1#
b00001010 (
b10000101 )
b10010010 *
#533
0#
#536
1#
b00001100 (
b10000110 )
b10010011 *
#537
0#
#540
1#
b00000001 '
b00001101 (
b10000111 )
b10010100 *
#541
0#
#544
1#
b00001110 (
b10001000 )
b10010101 *
#545
0#
#548
1#
b00000010 '
b00010000 (
b10001001 )
b10010110 *
#549
0#
#552
1#
b00000011 '
b00010010 (
b10001010 )
b10010111 *
#553
0#
#556
1#
b00010011 (
b10001011 )
b10011000 *
#557
0#
#560
1#
b00000100 '
b00010101 (
b10001100 )
b10011001 *
#561
0#
#564
1#
b00000101 '
b00010111 (
b10001101 )
b10011010 *
#565
0#
#568
1#
b00000110 '
b00011000 (
b10001110 )
b10011011 *
#569
0#
#572
1#
b00000111 '
b00011010 (
b10001111 )
b10011100 *
#573
0#
#576
1#
b00001000 '
b00011100 (
b10010000 )
b10011101 *
#577
0#
#580
1#
b00001001 '
b00011110 (
b10010001 )
b10011110 *
#581
0#
#584
1#
b00001010 '
b00100000 (
b10010010 )
b10011111 *
#585
0#
#588
1#
b00001100 '
b00100011 (
b10010011 )
b10100000 *
#589
0#
#592
1#
b00001101 '
b00100101 (
b10010100 )
b10100001 *
#593
0#
#596
1#
b00001110 '
b00100111 (
b10010101 )
b10100010 *
#597
0#
#600
1#
b00010000 '
b00101001 (
b10010110 )
b10100011 *
#601
0#
#604
1#
b00010010 '
b00101100 (
b10010111 )
b10100100 *
#605
0#
#608
1#
b00010011 '
b00101110 (
b10011000 )
b10100101 *
#609
0#
#612
1#
b00010101 '
b00110000 (
b10011001 )
b10100110 *
#613
0#
#616
1#
b00010111 '
b00110011 (
b10011010 )
b10100111 *
#617
0#
#620
1#
b00011000 '
b00110101 (
b10011011 )
b10101000 *
#621
0#
#624
1#
b00011010 '
b00111000 (
b10011100 )
b10101001 *
#625
0#
#628
1#
b00011100 '
b00111011 (
b10011101 )
b10101010 *
#629
0#
#632
1#
b00011110 '
b00111101 (
b10011110 )
b10101011 *
#633
0#
#636
1#
b00100000 '
b01000000 (
b10011111 )
b10101100 *
#637
0#
#640
1#
b00100011 '
b01000011 (
b10100000 )
b10101101 *
#641
0#
#644
1#
b00100101 '
b01000101 (
b10100001 )
b10101110 *
#645
0#
#648
1#
b00100111 '
b01001000 (
b10100010 )
b10101111 *
#649
0#
#652
1#
b00101001 '
b01001011 (
b10100011 )
b10110000 *
#653
0#
#656
1#
b00101100 '
b01001110 (
b10100100 )
b10110001 *
#657
0#
#660
1#
b00101110 '
b01010001 (
b10100101 )
b10110010 *
#661
0#
#664
1#
b00110000 '
b01010100 (
b10100110 )
b10110011 *
#665
0#
#668
1#
b00110011 '
b01010111 (
b10100111 )
b10110100 *
#669
0#
#672
1#
b00110101 '
b01011010 (
b10101000 )
b10110101 *
#673
0#
#676
1#
b00111000 '
b01011101 (
b10101001 )
b10110110 *
#677
0#
#680
1#
b00111011 '
b01100000 (
b10101010 )
b10110111 *
#681
0#
#684
1#
b00111101 '
b01100011 (
b10101011 )
b10111000 *
#685
0#
#688
1#
b01000000 '
b01100110 (
b10101100 )
b10111001 *
#689
0#
#692
1#
b01000011 '
b01101001 (
b10101101 )
b10111010 *
#693
0#
#696
1#
b01000101 '
b01101100 (
b10101110 )
b10111011 *
#697
0#
#700
1#
b01001000 '
b01101111 (
b10101111 )
b10111100 *
#701
0#
#704
1#
b01001011 '
b01110010 (
b10110000 )
b10111101 *
#705
0#
#708
1#
b01001110 '
b01110101 (
b10110001 )
b10111110 *
#709
0#
#712
1#
b01010001 '
b01111000 (
b10110010 )
b10111111 *
#713
0#
#716
1#
b01010100 '
b01111011 (
b10110011 )
b11000000 *
#717
0#
#720
1#
b01010111 '
b01111111 (
b10110100 )
b11000001 *
#721
0#
#724
1#
b01011010 '
b10000010 (
b10110101 )
b11000010 *
#725
0#
#728
1#
b01011101 '
b10000101 (
b10110110 )
b11000011 *
#729
0#
#732
1#
b01100000 '
b10001000 (
b10110111 )
b11000100 *
#733
0#
#736
1#
b01100011 '
b10001011 (
b10111000 )
b11000101 *
#737
0#
#740
1#
b01100110 '
b10001110 (
b10111001 )
b11000110 *
#741
0#
#744
1#
b01101001 '
b10010001 (
b10111010 )
b11000111 *
#745
0#
#748
1#
b01101100 '
b10010100 (
b10111011 )
b11001000 *
#749
0#
#752
1#
b01101111 '
b10010111 (
b10111100 )
b11001001 *
#753
0#
#756
1#
b01110010 '
b10011010 (
b10111101 )
b11001010 *
#757
0#
#760
1#
b01110101 '
b10011101 (
b10111110 )
b11001011 *
#761
0#
#764
1#
b01111000 '
b10100000 (
b10111111 )
b11001100 *
#765
0#
#768
1#
b01111011 '
b10100011 (
b11000000 )
b11001101 *
#769
0#
#772
1#
b01111111 '
b10100110 (
b11000001 )
b11001110 *
#773
0#
#776
1#
b10000010 '
b10101001 (
b11000010 )
b11001111 *
#777
0#
#780
1#
b10000101 '
b10101100 (
b11000011 )
b11010000 *
#781
0#
#784
1#
b10001000 '
b10101111 (
b11000100 )
b11010001 *
#785
0#
#788
1#
b10001011 '
b10110010 (
b11000101 )
b11010010 *
#789
0#
#792
1#
b10001110 '
b10110101 (
b11000110 )
b11010011 *
#793
0#
#796
1#
b10010001 '
b10111000 (
b11000111 )
b11010100 *
#797
0#
#800
1#
b10010100 '
b10111010 (
b11001000 )
b11010101 *
#801
0#
#804
1#
b10010111 '
b10111101 (
b11001001 )
b11010110 *
#805
0#
#808
1#
b10011010 '
b11000000 (
b11001010 )
b11010111 *
#809
0#
#812
1#
b10011101 '
b11000010 (
b11001011 )
b11011000 *
#813
0#
#816
1#
b10100000 '
b11000101 (
b11001100 )
b11011001 *
#817
0#
#820
1#
b10100011 '
b11001000 (
b11001101 )
b11011010 *
#821
0#
#824
1#
b10100110 '
b11001010 (
b11001110 )
b11011011 *
#825
0#
#828
1#
b10101001 '
b11001101 (
b11001111 )
b11011100 *
#829
0#
#832
1#
b10101100 '
b11001111 (
b11010000 )
b11011101 *
#833
0#
#836
1#
b10101111 '
b11010001 (
b11010001 )
b11011110 *
#837
0#
#840
1#
b10110010 '
b11010100 (
b11010010 )
b11011111 *
#841
0#
#844
1#
b10110101 '
b11010110 (
b11010011 )
b11100000 *
#845
0#
#848
1#
b10111000 '
b11011000 (
b11010100 )
b11100001 *
#849
0#
#852
1#
b10111010 '
b11011010 (
b11010101 )
b11100010 *
#853
0#
#856
1#
b10111101 '
b11011101 (
b11010110 )
b11100011 *
#857
0#
#860
1#
b11000000 '
b11011111 (
b11010111 )
b11100100 *
#861
0#
#864
1#
b11000010 '
b11100001 (
b11011000 )
b11100101 *
#865
0#
#868
1#
b11000101 '
b11100011 (
b11011001 )
b11100110 *
#869
0#
#872
1#
b11001000 '
b11100101 (
b11011010 )
b11100111 *
#873
0#
#876
1#
b11001010 '
b11100110 (
b11011011 )
b11101000 *
#877
0#
#880
1#
b11001101 '
b11101000 (
b11011100 )
b11101001 *
#881
0#
#884
1#
b11001111 '
b11101010 (
b11011101 )
b11101010 *
#885
0#
#888
1#
b11010001 '
b11101011 (
b11011110 )
b11101011 *
#889
0#
#892
1#
b11010100 '
b11101101 (
b11011111 )
b11101100 *
#893
0#
#896
1#
b11010110 '
b11101111 (
b11100000 )
b11101101 *
#897
0#
#900
1#
b11011000 '
b11110000 (
b11100001 )
b11101110 *
#901
0#
#904
1#
b11011010 '
b11110001 (
b11100010 )
b11101111 *
#905
0#
#908
1#
b11011101 '
b11110011 (
b11100011 )
b11110000 *
#909
0#
#912
1#
b11011111 '
b11110100 (
b11100100 )
b11110001 *
#913
0#
#916
1#
b11100001 '
b11110101 (
b11100101 )
b11110010 *
#917
0#
#920
1#
b11100011 '
b11110110 (
b11100110 )
b11110011 *
#921
0#
#924
1#
b11100101 '
b11110111 (
b11100111 )
b11110100 *
#925
0#
#928
1#
b11100110 '
b11111000 (
b11101000 )
b11110101 *
#929
0#
#932
1#
b11101000 '
b11111001 (
b11101001 )
b11110110 *
#933
0#
#936
1#
b11101010 '
b11111010 (
b11101010 )
b11110111 *
#937
0#
#940
1#
b11101011 '
b11101011 )
b11111000 *
#941
0#
#944
1#
b11101101 '
b11111011 (
b11101100 )
b11111001 *
#945
0#
#948
1#
b11101111 '
b11111100 (
b11101101 )
b11111010 *
#949
0#
#952
1#
b11110000 '
b11101110 )
b11111011 *
#953
0#
#956
1#
b11110001 '
b11111101 (
b11101111 )
b11111100 *
#957
0#
#960
1#
b11110011 '
b11110000 )
b11111101 *
#961
0#
#964
1#
b11110100 '
b11110001 )
b11111110 *
#965
0#
#968
1#
b11110101 '
b11110010 )
b11111111 *
#969
0#
#972
1#
b11110110 '
b11110011 )
b00000000 *
#973
0#
#976
1#
b11110111 '
b11111110 (
b11110100 )
b00000001 *
#977
0#
#980
1#
b11111000 '
b11111101 (
b11110101 )
b00000010 *
#981
0#
#984
1#
b11111001 '
b11110110 )
b00000011 *
#985
0#
#988
1#
b11111010 '
b11110111 )
b00000100 *
#989
0#
#992
1#
b11111000 )
b00000101 *
#993
0#
#996
1#
b11111011 '
b11111001 )
b00000110 *
#997
0#
#1000
1#
b11111100 '
b11111100 (
b11111010 )
b00000111 *
#1001
0#
#1004
1#
b11111011 )
b00001000 *
#1005
0#
#1008
1#
b11111101 '
b11111011 (
b11111100 )
b00001001 *
#1009
0#
#1012
1#
b11111010 (
b11111101 )
b00001010 *
#1013
0#
#1016
1#
b11111110 )
b00001011 *
#1017
0#
#1020
1#
b11111001 (
b11111111 )
b00001100 *
#1021
0#
#1024
1#
b11111000 (
b00000000 )
b00001101 *
#1025
0#
#1028
1#
b11111110 '
b11110111 (
b00000001 )
b00001110 *
#1029
0#
#1032
1#
b11111101 '
b11110110 (
b00000010 )
b00001111 *
#1033
0#
#1036
1#
b11110101 (
b00000011 )
b00010000 *
#1037
0#
#1040
1#
b11110100 (
b00000100 )
b00010001 *
#1041
0#
#1044
1#
b11110011 (
b00000101 )
b00010010 *
#1045
0#
#1048
1#
b11110001 (
b00000110 )
b00010011 *
#1049
0#
#1052
1#
b11111100 '
b11110000 (
b00000111 )
b00010100 *
#1053
0#
#1056
1#
b11101111 (
b00001000 )
b00010101 *
#1057
0#
#1060
1#
b11111011 '
b11101101 (
b00001001 )
b00010110 *
#1061
0#
#1064
1#
b11111010 '
b11101011 (
b00001010 )
b00010111 *
#1065
0#
#1068
1#
b11101010 (
b00001011 )
b00011000 *
#1069
0#
#1072
1#
b11111001 '
b11101000 (
b00001100 )
b00011001 *
#1073
0#
#1076
1#
b11111000 '
b11100110 (
b00001101 )
b00011010 *
#1077
0#
#1080
1#
b11110111 '
b11100101 (
b00001110 )
b00011011 *
#1081
0#
#1084
1#
b11110110 '
b11100011 (
b00001111 )
b00011100 *
#1085
0#
#1088
1#
b11110101 '
b11100001 (
b00010000 )
b00011101 *
#1089
0#
#1092
1#
b11110100 '
b11011111 (
b00010001 )
b00011110 *
#1093
0#
#1096
1#
b11110011 '
b11011101 (
b00010010 )
b00011111 *
#1097
0#
#1100
1#
b11110001 '
b11011010 (
b00010011 )
b00100000 *
#1101
0#
#1104
1#
b11110000 '
b11011000 (
b00010100 )
b00100001 *
#1105
0#
#1108
1#
b11101111 '
b11010110 (
b00010101 )
b00100010 *
#1109
0#
#1112
1#
b11101101 '
b11010100 (
b00010110 )
b00100011 *
#1113
0#
#1116
1#
b11101011 '
b11010001 (
b00010111 )
b00100100 *
#1117
0#
#1120
1#
b11101010 '
b11001111 (
b00011000 )
b00100101 *
#1121
0#
#1124
1#
b11101000 '
b11001101 (
b00011001 )
b00100110 *
#1125
0#
#1128
1#
b11100110 '
b11001010 (
b00011010 )
b00100111 *
#1129
0#
#1132
1#
b11100101 '
b11001000 (
b00011011 )
b00101000 *
#1133
0#
#1136
1#
b11100011 '
b11000101 (
b00011100 )
b00101001 *
#1137
0#
#1140
1#
b11100001 '
b11000010 (
b00011101 )
b00101010 *
#1141
0#
#1144
1#
b11011111 '
b11000000 (
b00011110 )
b00101011 *
#1145
0#
#1148
1#
b11011101 '
b10111101 (
b00011111 )
b00101100 *
#1149
0#
#1152
1#
b11011010 '
b10111010 (
b00100000 )
b00101101 *
#1153
0#
#1156
1#
b11011000 '
b10111000 (
b00100001 )
b00101110 *
#1157
0#
#1160
1#
b11010110 '
b10110101 (
b00100010 )
b00101111 *
#1161
0#
#1164
1#
b11010100 '
b10110010 (
b00100011 )
b00110000 *
#1165
0#
#1168
1#
b11010001 '
b10101111 (
b00100100 )
b00110001 *
#1169
0#
#1172
1#
b11001111 '
b10101100 (
b00100101 )
b00110010 *
#1173
0#
#1176
1#
b11001101 '
b10101001 (
b00100110 )
b00110011 *
#1177
0#
#1180
1#
b11001010 '
b10100110 (
b00100111 )
b00110100 *
#1181
0#
#1184
1#
b11001000 '
b10100011 (
b00101000 )
b00110101 *
#1185
0#
#1188
1#
b11000101 '
b10100000 (
b00101001 )
b00110110 *
#1189
0#
#1192
1#
b11000010 '
b10011101 (
b00101010 )
b00110111 *
#1193
0#
#1196
1#
b11000000 '
b10011010 (
b00101011 )
b00111000 *
#1197
0#
#1200
1#
b10111101 '
b10010111 (
b00101100 )
b00111001 *
#1201
0#
#1204
1#
b10111010 '
b10010100 (
b00101101 )
b00111010 *
#1205
0#
#1208
1#
b10111000 '
b10010001 (
b00101110 )
b00111011 *
#1209
0#
#1212
1#
b10110101 '
b10001110 (
b00101111 )
b00111100 *
#1213
0#
#1216
1#
b10110010 '
b10001011 (
b00110000 )
b00111101 *
#1217
0#
#1220
1#
b10101111 '
b10001000 (
b00110001 )
b00111110 *
#1221
0#
#1224
1#
b10101100 '
b10000101 (
b00110010 )
b00111111 *
#1225
0#
#1228
1#
b10101001 '
b10000010 (
b00110011 )
b01000000 *
#1229
0#
#1232
1#
b10100110 '
b01111110 (
b00110100 )
b01000001 *
#1233
0#
#1236
1#
b10100011 '
b01111011 (
b00110101 )
b01000010 *
#1237
0#
#1240
1#
b10100000 '
b01111000 (
b00110110 )
b01000011 *
#1241
0#
#1244
1#
b10011101 '
b01110101 (
b00110111 )
b01000100 *
#1245
0#
#1248
1#
b10011010 '
b01110010 (
b00111000 )
b01000101 *
#1249
0#
#1252
1#
b10010111 '
b01101111 (
b00111001 )
b01000110 *
#1253
0#
#1256
1#
b10010100 '
b01101100 (
b00111010 )
b01000111 *
#1257
0#
#1260
1#
b10010001 '
b01101001 (
b00111011 )
b01001000 *
#1261
0#
#1264
1#
b10001110 '
b01100110 (
b00111100 )
b01001001 *
#1265
0#
#1268
1#
b10001011 '
b01100011 (
b00111101 )
b01001010 *
#1269
0#
#1272
1#
b10001000 '
b01100000 (
b00111110 )
b01001011 *
#1273
0#
#1276
1#
b10000101 '
b01011101 (
b00111111 )
b01001100 *
#1277
0#
#1280
1#
b10000010 '
b01011010 (
b01000000 )
b01001101 *
#1281
0#
#1284
1#
b01111110 '
b01010111 (
b01000001 )
b01001110 *
#1285
0#
#1288
1#
b01111011 '
b01010100 (
b01000010 )
b01001111 *
#1289
0#
#1292
1#
b01111000 '
b01010001 (
b01000011 )
b01010000 *
#1293
0#
#1296
1#
b01110101 '
b01001110 (
b01000100 )
b01010001 *
#1297
0#
#1300
1#
b01110010 '
b01001011 (
b01000101 )
b01010010 *
#1301
0#
#1304
1#
b01101111 '
b01001000 (
b01000110 )
b01010011 *
#1305
0#
#1308
1#
b01101100 '
b01000101 (
b01000111 )
b01010100 *
#1309
0#
#1312
1#
b01101001 '
b01000011 (
b01001000 )
b01010101 *
#1313
0#
#1316
1#
b01100110 '
b01000000 (
b01001001 )
b01010110 *
#1317
0#
#1320
1#
b01100011 '
b00111101 (
b01001010 )
b01010111 *
#1321
0#
#1324
1#
b01100000 '
b00111011 (
b01001011 )
b01011000 *
#1325
0#
#1328
1#
b01011101 '
b00111000 (
b01001100 )
b01011001 *
#1329
0#
#1332
1#
b01011010 '
b00110101 (
b01001101 )
b01011010 *
#1333
0#
#1336
1#
b01010111 '
b00110011 (
b01001110 )
b01011011 *
#1337
0#
#1340
1#
b01010100 '
b00110000 (
b01001111 )
b01011100 *
#1341
0#
#1344
1#
b01010001 '
b00101110 (
b01010000 )
b01011101 *
#1345
0#
#1348
1#
b01001110 '
b00101100 (
b01010001 )
b01011110 *
#1349
0#
#1352
1#
b01001011 '
b00101001 (
b01010010 )
b01011111 *
#1353
0#
#1356
1#
b01001000 '
b00100111 (
b01010011 )
b01100000 *
